LICENSE.txt
MANIFEST.in
README.rst
requirements.txt
setup.py
SheetSync.egg-info/PKG-INFO
SheetSync.egg-info/SOURCES.txt
SheetSync.egg-info/dependency_links.txt
SheetSync.egg-info/requires.txt
SheetSync.egg-info/top_level.txt
docs/getting_started.rst
docs/index.rst
docs/module.rst
docs/tutorial.rst
sheetsync/__init__.py
sheetsync/version.py
sheetsync.egg-info/SOURCES.txt