Metadata-Version: 1.0
Name: sheetsync
Version: 0.2.2
Summary: Synchronize rows of data with a google spreadsheet
Home-page: https://github.com/mbrenig/SheetSync/
Author: Mark Brenig-Jones
Author-email: markbrenigjones@gmail.com
License: UNKNOWN
Platform: any
Classifier: Development Status :: 4 - Beta
Classifier: License :: OSI Approved :: MIT License
Classifier: Programming Language :: Python :: 2.7
